polars_root/__init__.py
polars_root/functions.py
polars_root/py.typed
polars_root-0.1.1.dist-info/METADATA
polars_root-0.1.1.dist-info/WHEEL
polars_root-0.1.1.dist-info/licenses/LICENSE
polars_root-0.1.1.dist-info/RECORD
