Metadata-Version: 2.4
Name: polars-root
Version: 0.1.1
Summary: Polars plugin for reading CERN's ROOT file format
Project-URL: Homepage, https://github.com/DanielMaysWilliams/polars-root
Author-email: Daniel Williams <daniel.mays.williams@gmail.com>
License: MIT License
License-File: LICENSE
Keywords: dataframe,polars,root
Classifier: Programming Language :: Python :: 3 :: Only
Classifier: Programming Language :: Python :: 3.10
Classifier: Programming Language :: Python :: 3.11
Classifier: Programming Language :: Python :: 3.12
Classifier: Programming Language :: Python :: 3.13
Classifier: Topic :: Scientific/Engineering :: Physics
Requires-Python: >=3.10
Requires-Dist: awkward>=2
Requires-Dist: awkward>=2.7; python_version >= '3.13'
Requires-Dist: pyarrow>=15
Requires-Dist: pyarrow>=18; python_version >= '3.13'
Requires-Dist: uproot>=5.4
Provides-Extra: standard
Requires-Dist: polars>=1.22; extra == 'standard'
Provides-Extra: u64-idx
Requires-Dist: polars-u64-idx>=1.22; extra == 'u64-idx'
